qinglan_bot/__init__.py
qinglan_bot/config.py
qinglan_bot/database/__init__.py
qinglan_bot/database/model.py
qinglan_bot/plugins/__init__.py
qinglan_bot/plugins/link/__init__.py
qinglan_bot/plugins/link/add.py
qinglan_bot/plugins/link/delete.py
qinglan_bot/plugins/message/__init__.py
qinglan_bot/plugins/message/on_mc.py
qinglan_bot/plugins/message/on_platform.py
qinglan_bot/service/__init__.py
qinglan_bot/service/target.py
qinglan_bot/utils/__init__.py
qinglan_bot/utils/rule.py
qinglan_bot/utils/tool.py
qinglan_bot-0.1.7.dist-info/licenses/LICENSE
qinglan_bot-0.1.7.dist-info/METADATA
qinglan_bot-0.1.7.dist-info/WHEEL
qinglan_bot-0.1.7.dist-info/top_level.txt
qinglan_bot-0.1.7.dist-info/RECORD
