Metadata-Version: 2.4
Name: qinglan-bot
Version: 0.1.7
Summary: 基于NoneBot2与鹊桥的Minecraft Server消息互通机器人
Requires-Python: >=3.10
License-File: LICENSE
Requires-Dist: nonebot-adapter-minecraft>=1.5.1
Requires-Dist: nonebot-plugin-alconna>=0.59.3
Requires-Dist: nonebot-plugin-orm[sqlite]>=0.8.2
Requires-Dist: nonebot-plugin-uninfo>=0.9.0
Requires-Dist: nonebot2[fastapi,httpx,websockets]<3,>=2.4.2
Dynamic: license-file
